{
  "schema_version": 1,
  "run_id": "a9bfd151-2821-45b5-a902-c85ac82651b8",
  "gate_key": "cargo-ci",
  "stage": "postcheck",
  "issue_id": "690f618a-6b40-44b2-969d-582335cf768f",
  "commit": "d4190210e32473ed2524d9ec4a47aac2410625f4",
  "branch": "main",
  "status": "passed",
  "started_at": "2026-06-10T15:43:01.150014066Z",
  "completed_at": "2026-06-10T15:44:27.224970532Z",
  "duration_ms": 86074,
  "exit_code": 0,
  "stdout": "  ✓ fmt: ok\n  ✓ clippy: ok\n  ✓ test: 1897 passed, 0 failed, 9 ignored\n\n",
  "stderr": "",
  "command": "cargo fmt --all -- --check && cargo clippy --workspace --all-targets -- -D warnings && cargo test --workspace",
  "by": "auto:executor",
  "message": null
}