{
  "id": "9db27a3a-86c5-4d79-9582-9ad68364ea36",
  "title": "Version 1.0 Production Release",
  "description": "First stable production release of just-in-time with complete gate system and documentation",
  "state": "backlog",
  "priority": "critical",
  "assignee": null,
  "dependencies": [
    "4a00b2b0-a527-4f04-9475-62f1d838f903",
    "9d427a6b-a8f7-4478-a0e1-1637781e00f6",
    "d7bfd4a4-b2ad-477a-977e-e3242b77b7a2",
    "5fe00921-6548-4263-b428-f1e839f68c74",
    "93f3e4df-990c-4993-b8dc-66a8827acba7"
  ],
  "gates_required": [
    "code-review"
  ],
  "gates_status": {},
  "context": {},
  "documents": [
    {
      "path": "ROADMAP.md",
      "commit": null,
      "label": "Roadmap",
      "doc_type": null
    }
  ],
  "labels": [
    "type:milestone",
    "milestone:v1.0"
  ]
}