{
  "id": "a0f0f342-5147-4775-b002-3c28d363460e",
  "title": "Re-express existing checks as default rules with [validation] aliases",
  "description": "Implements decision record (dev/active/f6a704d0-validation-engine.md) section 8.3.\n\n## Success Criteria\n\n- [hard] The COMPLETE set of existing checks is re-expressed as default rules: type-label requirement, label format, namespace-registry, orphan-leaf, strategic-label consistency, and per-namespace allowed-values/value-pattern/uniqueness/required.\n- [hard] Default rules preserve today's warn-vs-reject behavior via enforce (default false); parity is covered by tests.\n- [hard] No legacy [validation] or [namespaces] enforcement remains hard-coded in validation.rs/validate.rs.\n",
  "state": "backlog",
  "priority": "normal",
  "assignee": null,
  "dependencies": [
    "b8ba1b10-09f3-4807-90cb-95b91258347d"
  ],
  "gates_required": [
    "cargo-ci",
    "code-review"
  ],
  "gates_status": {},
  "context": {},
  "documents": [],
  "labels": [
    "type:task",
    "epic:validation-engine"
  ],
  "created_at": "2026-06-06T15:51:20.563449834+00:00",
  "updated_at": "2026-06-06T16:05:03.257731069+00:00"
}